02_Verilog_Demo/rtl/design6_seq.v
// Sequential, resource-optimized implementation of Design 6 adder.
module design6_seq #(parameter WIDTH = 4) (
    input  wire                   clk,
    input  wire                   rst_n,
    input  wire                   start,
    input  wire [WIDTH-1:0]       A,
    input  wire [WIDTH-1:0]       B,
    input  wire [WIDTH-1:0]       C,
    input  wire [WIDTH-1:0]       D,
    output reg  [WIDTH+1:0]       F,
    output reg                    valid
);
    reg [1:0] mux_sel;
    reg       clear_acc;
    reg       enable_acc;
    reg       load_output;

    reg [WIDTH-1:0] mux_out;
    wire [WIDTH+1:0] add_out;
    reg  [WIDTH+1:0] acc_reg;

    localparam IDLE  = 3'd0,
               ADD_A = 3'd1,
               ADD_B = 3'd2,
               ADD_C = 3'd3,
               ADD_D = 3'd4,
               DONE  = 3'd5;

    reg [2:0] current_state, next_state;

    always @(*) begin
        case (mux_sel)
            2'b00: mux_out = A;
            2'b01: mux_out = B;
            2'b10: mux_out = C;
            2'b11: mux_out = D;
            default: mux_out = {WIDTH{1'b0}};
        endcase
    end

    assign add_out = mux_out + acc_reg;

    always @(posedge clk or negedge rst_n) begin
        if (!rst_n)
            acc_reg <= {WIDTH+2{1'b0}};
        else if (clear_acc)
            acc_reg <= {WIDTH+2{1'b0}};
        else if (enable_acc)
            acc_reg <= add_out;
    end

    always @(posedge clk or negedge rst_n) begin
        if (!rst_n) begin
            F <= {WIDTH+2{1'b0}};
            valid <= 1'b0;
        end else if (load_output) begin
            F <= acc_reg;
            valid <= 1'b1;
        end else begin
            valid <= 1'b0;
        end
    end

    always @(posedge clk or negedge rst_n) begin
        if (!rst_n)
            current_state <= IDLE;
        else
            current_state <= next_state;
    end

    always @(*) begin
        next_state  = current_state;
        mux_sel     = 2'b00;
        clear_acc   = 1'b0;
        enable_acc  = 1'b0;
        load_output = 1'b0;

        case (current_state)
            IDLE: begin
                clear_acc = 1'b1;
                if (start)
                    next_state = ADD_A;
            end
            ADD_A: begin
                mux_sel    = 2'b00;
                enable_acc = 1'b1;
                next_state = ADD_B;
            end
            ADD_B: begin
                mux_sel    = 2'b01;
                enable_acc = 1'b1;
                next_state = ADD_C;
            end
            ADD_C: begin
                mux_sel    = 2'b10;
                enable_acc = 1'b1;
                next_state = ADD_D;
            end
            ADD_D: begin
                mux_sel    = 2'b11;
                enable_acc = 1'b1;
                next_state = DONE;
            end
            DONE: begin
                load_output = 1'b1;
                next_state  = IDLE;
            end
            default: begin
                next_state = IDLE;
            end
        endcase
    end
endmodule

RTL2GDS_WS_Files/rtl/tb_design6.v
`timescale 1ns/1ps

module tb_design6;
    localparam WIDTH = 4;

    reg clk;
    reg rst_n;
    reg start;
    reg [WIDTH-1:0] A, B, C, D;
    wire [WIDTH+1:0] F;
    wire valid;

    design6_seq #(.WIDTH(WIDTH)) dut (
        .clk(clk),
        .rst_n(rst_n),
        .start(start),
        .A(A),
        .B(B),
        .C(C),
        .D(D),
        .F(F),
        .valid(valid)
    );

    initial begin
        clk = 0;
        forever #5 clk = ~clk;
    end

    initial begin
        $dumpfile("design6.vcd");
        $dumpvars(0, tb_design6);
    end

    initial begin
        rst_n = 0;
        start = 0;
        A = 0; B = 0; C = 0; D = 0;
        repeat (2) @(posedge clk);
        rst_n = 1;

        @(posedge clk);
        A = 4'd3; B = 4'd5; C = 4'd7; D = 4'd2;
        start = 1;
        @(posedge clk);
        start = 0;

        wait (valid);
        if (F !== (A + B + C + D)) begin
            $display("ERROR: Expected %0d, got %0d", A + B + C + D, F);
        end else begin
            $display("PASS: Result %0d valid", F);
        end

        repeat (5) @(posedge clk);
        $finish;
    end
endmodule

RTL2GDS_WS_Files/rtl/design6.vcd
$date
	Thu Jan  8 13:23:28 2026
$end
$version
	Icarus Verilog
$end
$timescale
	1ps
$end
$scope module tb_design6 $end
$var wire 1 ! valid $end
$var wire 6 " F [5:0] $end
$var parameter 32 # WIDTH $end
$var reg 4 $ A [3:0] $end
$var reg 4 % B [3:0] $end
$var reg 4 & C [3:0] $end
$var reg 4 ' D [3:0] $end
$var reg 1 ( clk $end
$var reg 1 ) rst_n $end
$var reg 1 * start $end
$scope module dut $end
$var wire 4 + A [3:0] $end
$var wire 4 , B [3:0] $end
$var wire 4 - C [3:0] $end
$var wire 4 . D [3:0] $end
$var wire 1 ( clk $end
$var wire 1 ) rst_n $end
$var wire 1 * start $end
$var wire 6 / add_out [5:0] $end
$var parameter 3 0 ADD_A $end
$var parameter 3 1 ADD_B $end
$var parameter 3 2 ADD_C $end
$var parameter 3 3 ADD_D $end
$var parameter 3 4 DONE $end
$var parameter 3 5 IDLE $end
$var parameter 32 6 WIDTH $end
$var reg 6 7 F [5:0] $end
$var reg 6 8 acc_reg [5:0] $end
$var reg 1 9 clear_acc $end
$var reg 3 : current_state [2:0] $end
$var reg 1 ; enable_acc $end
$var reg 1 < load_output $end
$var reg 4 = mux_out [3:0] $end
$var reg 2 > mux_sel [1:0] $end
$var reg 3 ? next_state [2:0] $end
$var reg 1 ! valid $end
$upscope $end
$upscope $end
$enddefinitions $end
$comment Show the parameter values. $end
$dumpall
b100 6
b0 5
b101 4
b100 3
b11 2
b10 1
b1 0
b100 #
$end
#0
$dumpvars
b0 ?
b0 >
b0 =
0<
0;
b0 :
19
b0 8
b0 7
b0 /
b0 .
b0 -
b0 ,
b0 +
0*
0)
0(
b0 '
b0 &
b0 %
b0 $
b0 "
0!
$end
#5000
1(
#10000
0(
#15000
1)
1(
#20000
0(
#25000
b1 ?
19
b11 /
b11 =
1*
b10 '
b10 .
b111 &
b111 -
b101 %
b101 ,
b11 $
b11 +
1(
#30000
0(
#35000
1;
b1 :
09
b10 ?
0*
1(
#40000
0(
#45000
b101 =
b11 ?
b1 >
1;
b10 :
b1000 /
b11 8
1(
#50000
0(
#55000
b111 =
b100 ?
1;
b10 >
b1111 /
b1000 8
b11 :
1(
#60000
0(
#65000
b10 =
b101 ?
1;
b11 >
b100 :
b10001 /
b1111 8
1(
#70000
0(
#75000
b11 =
b0 ?
1<
0;
b0 >
b10100 /
b10001 8
b101 :
1(
#80000
0(
#85000
19
0<
b0 :
1!
b10001 "
b10001 7
1(
#90000
0(
#95000
b11 /
b0 8
0!
1(
